bizfly_two_fa/__init__.py
bizfly_two_fa/constants/__init__.py
bizfly_two_fa/utils/__init__.py
bizfly_two_fa/utils/decorators.py
bizfly_two_fa/utils/methods.py
tests/__init__.py
tests/gen_session.py
bizfly_two_fa-1.0.5.dist-info/LICENSE
bizfly_two_fa-1.0.5.dist-info/METADATA
bizfly_two_fa-1.0.5.dist-info/WHEEL
bizfly_two_fa-1.0.5.dist-info/top_level.txt
bizfly_two_fa-1.0.5.dist-info/RECORD
