Metadata-Version: 2.1
Name: bizfly-two-fa
Version: 1.0.5
Summary: Python SDK for Bizfly2FA
Home-page: https://github.com/shinrel22/python_bizfly_two_fa
Author: Tri Nguyen
Author-email: tringuyen5835@gmail.com
License: MIT
Platform: UNKNOWN
Classifier: Intended Audience :: Developers
Classifier: License :: OSI Approved :: MIT License
Classifier: Operating System :: OS Independent
Classifier: Programming Language :: Python
Classifier: Topic :: Software Development :: Libraries :: Python Modules
Requires-Python: >=2.7
Requires-Dist: requests
